README.md
setup.py
python/basskick/__init__.py
python/basskick.egg-info/PKG-INFO
python/basskick.egg-info/SOURCES.txt
python/basskick.egg-info/dependency_links.txt
python/basskick.egg-info/entry_points.txt
python/basskick.egg-info/requires.txt
python/basskick.egg-info/top_level.txt
python/basskick/api/__init__.py
python/basskick/api/benv.py
python/basskick/api/packon.py
python/basskick/api/system.py
python/basskick/cli/__init__.py
python/basskick/packon/__init__.py
python/basskick/packon/build.py